LICENSE.txt
MANIFEST.in
README.rst
VERSION
__init__.py
example.py
pip_requirements.txt
sandbox.py
setup.py
proauth2/__init__.py
proauth2/async_proauth2.py
proauth2/auth_methods.py
proauth2/proauth2.py
proauth2.egg-info/PKG-INFO
proauth2.egg-info/SOURCES.txt
proauth2.egg-info/dependency_links.txt
proauth2.egg-info/requires.txt
proauth2.egg-info/top_level.txt
proauth2/data_stores/__init__.py
proauth2/data_stores/async_mongo_ds.py
proauth2/data_stores/mongo_ds.py
proauth2/data_stores/validate.py
test/test_async_proauth2.py
test/test_proauth2.py