Metadata-Version: 1.0
Name: proauth2
Version: 1.2.1
Summary: An OAuth2 Provider Module for Python
Home-page: https://github.com/charlesthomas/proauth2
Author: Charles Thomas
Author-email: ch@rlesthom.as
License: MIT
Platform: UNKNOWN
